{
    "orgName": "cjung ",
    "edition": "Enterprise",
    "features": [
        "Communities",
        "ServiceCloud",
        "Chatbot"
        "LIVEAGENT"
    ],
    "settings": {
        "orgPreferenceSettings": {
            "networksEnabled": true,
            "s1DesktopEnabled": true,
            "s1EncryptedStoragePref2": false
        },
        "omniChannelSettings": {
            "enableOmniChannel": true
        },
        "liveAgentSettings": {
            "enableLiveAgent": true
          }
    }
}